{
	"configurations" : 
	[
		{
			"directories" : 
			[
				{
					"build" : ".",
					"jsonFile" : "directory-.-Debug-d0094a50bb2071803777.json",
					"minimumCMakeVersion" : 
					{
						"string" : "3.26"
					},
					"projectIndex" : 0,
					"source" : ".",
					"targetIndexes" : 
					[
						0,
						1,
						2,
						3,
						4,
						5,
						6,
						7,
						8,
						9,
						10,
						11,
						12,
						13,
						14,
						15,
						16,
						17,
						18,
						19,
						20,
						21,
						22,
						23,
						24,
						25,
						26,
						27,
						28,
						29,
						30,
						31,
						32,
						33,
						34,
						35,
						36,
						37,
						38,
						39,
						40,
						41,
						42,
						43,
						44,
						45,
						46,
						47,
						48,
						49,
						50,
						51,
						52,
						53,
						54,
						55,
						56,
						57,
						58,
						59,
						60,
						61,
						62,
						63,
						64,
						65,
						66,
						67,
						68,
						69,
						70,
						71,
						72,
						73,
						74,
						75,
						76,
						77,
						78,
						79,
						80,
						81,
						82,
						83,
						84,
						85,
						86,
						87,
						88,
						89,
						90,
						91,
						92,
						93,
						94,
						95,
						96,
						97,
						98,
						99,
						100,
						101,
						102,
						103,
						104,
						105,
						106,
						107,
						108,
						109,
						110,
						111,
						112,
						113,
						114,
						115,
						116,
						117,
						118,
						119,
						120,
						121,
						122,
						123,
						124,
						125,
						126,
						127,
						128,
						129,
						130,
						131,
						132,
						133,
						134,
						135,
						136,
						137,
						138,
						139,
						140,
						141,
						142,
						143,
						144,
						145,
						146,
						147,
						148,
						149,
						150,
						151,
						152,
						153,
						154,
						155,
						156,
						157,
						158,
						159,
						160,
						161,
						162,
						163,
						164,
						165,
						166,
						167,
						168,
						169,
						170,
						171,
						172,
						173,
						174,
						175,
						176,
						177,
						178,
						179,
						180,
						181,
						182,
						183,
						184,
						185,
						186,
						187,
						188,
						189,
						190,
						191,
						192,
						193,
						194,
						195,
						196,
						197,
						198,
						199,
						200,
						201,
						202,
						203,
						204,
						205,
						206,
						207,
						208,
						209,
						210,
						211,
						212,
						213,
						214,
						215,
						216,
						217,
						218,
						219,
						220,
						221,
						222,
						223,
						224,
						225,
						226,
						227,
						228,
						229,
						230,
						231,
						232,
						233,
						234,
						235,
						236,
						237,
						238,
						239,
						240,
						241,
						242,
						243,
						244,
						245,
						246,
						247,
						248,
						249,
						250,
						251,
						252,
						253,
						254,
						255,
						256,
						257,
						258,
						259,
						260,
						261,
						262,
						263,
						264
					]
				}
			],
			"name" : "Debug",
			"projects" : 
			[
				{
					"directoryIndexes" : 
					[
						0
					],
					"name" : "SP2023",
					"targetIndexes" : 
					[
						0,
						1,
						2,
						3,
						4,
						5,
						6,
						7,
						8,
						9,
						10,
						11,
						12,
						13,
						14,
						15,
						16,
						17,
						18,
						19,
						20,
						21,
						22,
						23,
						24,
						25,
						26,
						27,
						28,
						29,
						30,
						31,
						32,
						33,
						34,
						35,
						36,
						37,
						38,
						39,
						40,
						41,
						42,
						43,
						44,
						45,
						46,
						47,
						48,
						49,
						50,
						51,
						52,
						53,
						54,
						55,
						56,
						57,
						58,
						59,
						60,
						61,
						62,
						63,
						64,
						65,
						66,
						67,
						68,
						69,
						70,
						71,
						72,
						73,
						74,
						75,
						76,
						77,
						78,
						79,
						80,
						81,
						82,
						83,
						84,
						85,
						86,
						87,
						88,
						89,
						90,
						91,
						92,
						93,
						94,
						95,
						96,
						97,
						98,
						99,
						100,
						101,
						102,
						103,
						104,
						105,
						106,
						107,
						108,
						109,
						110,
						111,
						112,
						113,
						114,
						115,
						116,
						117,
						118,
						119,
						120,
						121,
						122,
						123,
						124,
						125,
						126,
						127,
						128,
						129,
						130,
						131,
						132,
						133,
						134,
						135,
						136,
						137,
						138,
						139,
						140,
						141,
						142,
						143,
						144,
						145,
						146,
						147,
						148,
						149,
						150,
						151,
						152,
						153,
						154,
						155,
						156,
						157,
						158,
						159,
						160,
						161,
						162,
						163,
						164,
						165,
						166,
						167,
						168,
						169,
						170,
						171,
						172,
						173,
						174,
						175,
						176,
						177,
						178,
						179,
						180,
						181,
						182,
						183,
						184,
						185,
						186,
						187,
						188,
						189,
						190,
						191,
						192,
						193,
						194,
						195,
						196,
						197,
						198,
						199,
						200,
						201,
						202,
						203,
						204,
						205,
						206,
						207,
						208,
						209,
						210,
						211,
						212,
						213,
						214,
						215,
						216,
						217,
						218,
						219,
						220,
						221,
						222,
						223,
						224,
						225,
						226,
						227,
						228,
						229,
						230,
						231,
						232,
						233,
						234,
						235,
						236,
						237,
						238,
						239,
						240,
						241,
						242,
						243,
						244,
						245,
						246,
						247,
						248,
						249,
						250,
						251,
						252,
						253,
						254,
						255,
						256,
						257,
						258,
						259,
						260,
						261,
						262,
						263,
						264
					]
				}
			],
			"targets" : 
			[
				{
					"directoryIndex" : 0,
					"id" : "10ta::@6890427a1f51a3e7e1df",
					"jsonFile" : "target-10ta-Debug-61e26aefeddcc0c4451c.json",
					"name" : "10ta",
					"projectIndex" : 0
				},
				{
					"directoryIndex" : 0,
					"id" : "10taSoFunkcii::@6890427a1f51a3e7e1df",
					"jsonFile" : "target-10taSoFunkcii-Debug-bc5d92e89c7a769e8d04.json",
					"name" : "10taSoFunkcii",
					"projectIndex" : 0
				},
				{
					"directoryIndex" : 0,
					"id" : "11ta::@6890427a1f51a3e7e1df",
					"jsonFile" : "target-11ta-Debug-e457ad2bbe88a00f6002.json",
					"name" : "11ta",
					"projectIndex" : 0
				},
				{
					"directoryIndex" : 0,
					"id" : "11taSoFunkcii::@6890427a1f51a3e7e1df",
					"jsonFile" : "target-11taSoFunkcii-Debug-fcff4d66d6e76673deb2.json",
					"name" : "11taSoFunkcii",
					"projectIndex" : 0
				},
				{
					"directoryIndex" : 0,
					"id" : "12ta::@6890427a1f51a3e7e1df",
					"jsonFile" : "target-12ta-Debug-16495cbc624eec83f8c6.json",
					"name" : "12ta",
					"projectIndex" : 0
				},
				{
					"directoryIndex" : 0,
					"id" : "12ta-2::@6890427a1f51a3e7e1df",
					"jsonFile" : "target-12ta-2-Debug-bd84011b1fd5ddb6ea38.json",
					"name" : "12ta-2",
					"projectIndex" : 0
				},
				{
					"directoryIndex" : 0,
					"id" : "12taB2B::@6890427a1f51a3e7e1df",
					"jsonFile" : "target-12taB2B-Debug-26d6f89057b19413557f.json",
					"name" : "12taB2B",
					"projectIndex" : 0
				},
				{
					"directoryIndex" : 0,
					"id" : "13ta::@6890427a1f51a3e7e1df",
					"jsonFile" : "target-13ta-Debug-50ecc9ca3a6689f29ee9.json",
					"name" : "13ta",
					"projectIndex" : 0
				},
				{
					"directoryIndex" : 0,
					"id" : "13ta-2::@6890427a1f51a3e7e1df",
					"jsonFile" : "target-13ta-2-Debug-07351bfb5ac120370153.json",
					"name" : "13ta-2",
					"projectIndex" : 0
				},
				{
					"directoryIndex" : 0,
					"id" : "14ta-2::@6890427a1f51a3e7e1df",
					"jsonFile" : "target-14ta-2-Debug-e4926fae21fb1ede04da.json",
					"name" : "14ta-2",
					"projectIndex" : 0
				},
				{
					"directoryIndex" : 0,
					"id" : "15ta-2::@6890427a1f51a3e7e1df",
					"jsonFile" : "target-15ta-2-Debug-a85735ba0b8ecfa9c96c.json",
					"name" : "15ta-2",
					"projectIndex" : 0
				},
				{
					"directoryIndex" : 0,
					"id" : "16ta-2::@6890427a1f51a3e7e1df",
					"jsonFile" : "target-16ta-2-Debug-0b7884fce061da4a470b.json",
					"name" : "16ta-2",
					"projectIndex" : 0
				},
				{
					"directoryIndex" : 0,
					"id" : "17ta-2::@6890427a1f51a3e7e1df",
					"jsonFile" : "target-17ta-2-Debug-f9ced58cb41139201f17.json",
					"name" : "17ta-2",
					"projectIndex" : 0
				},
				{
					"directoryIndex" : 0,
					"id" : "18ta-2::@6890427a1f51a3e7e1df",
					"jsonFile" : "target-18ta-2-Debug-600029dd25e31b66b6c8.json",
					"name" : "18ta-2",
					"projectIndex" : 0
				},
				{
					"directoryIndex" : 0,
					"id" : "1va::@6890427a1f51a3e7e1df",
					"jsonFile" : "target-1va-Debug-8f4bc94be56ea22da7cf.json",
					"name" : "1va",
					"projectIndex" : 0
				},
				{
					"directoryIndex" : 0,
					"id" : "2ra::@6890427a1f51a3e7e1df",
					"jsonFile" : "target-2ra-Debug-72f002e65471791d0ab6.json",
					"name" : "2ra",
					"projectIndex" : 0
				},
				{
					"directoryIndex" : 0,
					"id" : "2ra-D2::@6890427a1f51a3e7e1df",
					"jsonFile" : "target-2ra-D2-Debug-838a3281143f8c9df39b.json",
					"name" : "2ra-D2",
					"projectIndex" : 0
				},
				{
					"directoryIndex" : 0,
					"id" : "2raB2B::@6890427a1f51a3e7e1df",
					"jsonFile" : "target-2raB2B-Debug-b9cb4e5e7b2c2eafb7a3.json",
					"name" : "2raB2B",
					"projectIndex" : 0
				},
				{
					"directoryIndex" : 0,
					"id" : "3brojaRedosled::@6890427a1f51a3e7e1df",
					"jsonFile" : "target-3brojaRedosled-Debug-148805b54813faca3305.json",
					"name" : "3brojaRedosled",
					"projectIndex" : 0
				},
				{
					"directoryIndex" : 0,
					"id" : "3ta::@6890427a1f51a3e7e1df",
					"jsonFile" : "target-3ta-Debug-8ef600e2fadfc2ca4bf7.json",
					"name" : "3ta",
					"projectIndex" : 0
				},
				{
					"directoryIndex" : 0,
					"id" : "3ta-2::@6890427a1f51a3e7e1df",
					"jsonFile" : "target-3ta-2-Debug-4604eb134a5d6a0b5029.json",
					"name" : "3ta-2",
					"projectIndex" : 0
				},
				{
					"directoryIndex" : 0,
					"id" : "4broja01::@6890427a1f51a3e7e1df",
					"jsonFile" : "target-4broja01-Debug-679b5fbb7abc3ef91b27.json",
					"name" : "4broja01",
					"projectIndex" : 0
				},
				{
					"directoryIndex" : 0,
					"id" : "4ta::@6890427a1f51a3e7e1df",
					"jsonFile" : "target-4ta-Debug-ad803adcdb137c0b9791.json",
					"name" : "4ta",
					"projectIndex" : 0
				},
				{
					"directoryIndex" : 0,
					"id" : "4ta-2::@6890427a1f51a3e7e1df",
					"jsonFile" : "target-4ta-2-Debug-7b2bc9c0880e67dca106.json",
					"name" : "4ta-2",
					"projectIndex" : 0
				},
				{
					"directoryIndex" : 0,
					"id" : "4taB2B::@6890427a1f51a3e7e1df",
					"jsonFile" : "target-4taB2B-Debug-c325dab3897f14096248.json",
					"name" : "4taB2B",
					"projectIndex" : 0
				},
				{
					"directoryIndex" : 0,
					"id" : "5cifrenSpecial::@6890427a1f51a3e7e1df",
					"jsonFile" : "target-5cifrenSpecial-Debug-f2c25c30150068578aa4.json",
					"name" : "5cifrenSpecial",
					"projectIndex" : 0
				},
				{
					"directoryIndex" : 0,
					"id" : "5ta::@6890427a1f51a3e7e1df",
					"jsonFile" : "target-5ta-Debug-09a5b9c6057f76e1266f.json",
					"name" : "5ta",
					"projectIndex" : 0
				},
				{
					"directoryIndex" : 0,
					"id" : "5taB2B::@6890427a1f51a3e7e1df",
					"jsonFile" : "target-5taB2B-Debug-38d2261cdc14f7155abc.json",
					"name" : "5taB2B",
					"projectIndex" : 0
				},
				{
					"directoryIndex" : 0,
					"id" : "6ta::@6890427a1f51a3e7e1df",
					"jsonFile" : "target-6ta-Debug-2089f2eb988941697e3a.json",
					"name" : "6ta",
					"projectIndex" : 0
				},
				{
					"directoryIndex" : 0,
					"id" : "6ta-2::@6890427a1f51a3e7e1df",
					"jsonFile" : "target-6ta-2-Debug-fc1c8608d78c73f8b508.json",
					"name" : "6ta-2",
					"projectIndex" : 0
				},
				{
					"directoryIndex" : 0,
					"id" : "6taB2B::@6890427a1f51a3e7e1df",
					"jsonFile" : "target-6taB2B-Debug-98e88e421484319f6135.json",
					"name" : "6taB2B",
					"projectIndex" : 0
				},
				{
					"directoryIndex" : 0,
					"id" : "7ma::@6890427a1f51a3e7e1df",
					"jsonFile" : "target-7ma-Debug-d80ac9c4a8c06b096feb.json",
					"name" : "7ma",
					"projectIndex" : 0
				},
				{
					"directoryIndex" : 0,
					"id" : "7ta-2::@6890427a1f51a3e7e1df",
					"jsonFile" : "target-7ta-2-Debug-065c0215ca0392a508af.json",
					"name" : "7ta-2",
					"projectIndex" : 0
				},
				{
					"directoryIndex" : 0,
					"id" : "8ma::@6890427a1f51a3e7e1df",
					"jsonFile" : "target-8ma-Debug-38dc1bcb349fa7a5d21d.json",
					"name" : "8ma",
					"projectIndex" : 0
				},
				{
					"directoryIndex" : 0,
					"id" : "8maB2B::@6890427a1f51a3e7e1df",
					"jsonFile" : "target-8maB2B-Debug-2d65fe1b2f8e086feeed.json",
					"name" : "8maB2B",
					"projectIndex" : 0
				},
				{
					"directoryIndex" : 0,
					"id" : "9ta::@6890427a1f51a3e7e1df",
					"jsonFile" : "target-9ta-Debug-c0e88885d9c32c7c9f9f.json",
					"name" : "9ta",
					"projectIndex" : 0
				},
				{
					"directoryIndex" : 0,
					"id" : "9ta-2::@6890427a1f51a3e7e1df",
					"jsonFile" : "target-9ta-2-Debug-7f68e41169acb05cbb3d.json",
					"name" : "9ta-2",
					"projectIndex" : 0
				},
				{
					"directoryIndex" : 0,
					"id" : "AbsZadaca::@6890427a1f51a3e7e1df",
					"jsonFile" : "target-AbsZadaca-Debug-591d9cf46ec5fc1d3003.json",
					"name" : "AbsZadaca",
					"projectIndex" : 0
				},
				{
					"directoryIndex" : 0,
					"id" : "AbsolutnaRazlika::@6890427a1f51a3e7e1df",
					"jsonFile" : "target-AbsolutnaRazlika-Debug-153c062f9e632fa8ef7d.json",
					"name" : "AbsolutnaRazlika",
					"projectIndex" : 0
				},
				{
					"directoryIndex" : 0,
					"id" : "AkademskoOcenuvanje::@6890427a1f51a3e7e1df",
					"jsonFile" : "target-AkademskoOcenuvanje-Debug-54849dda0d65654cb752.json",
					"name" : "AkademskoOcenuvanje",
					"projectIndex" : 0
				},
				{
					"directoryIndex" : 0,
					"id" : "Aud1.1::@6890427a1f51a3e7e1df",
					"jsonFile" : "target-Aud1.1-Debug-2501ddd28b8e773ce6be.json",
					"name" : "Aud1.1",
					"projectIndex" : 0
				},
				{
					"directoryIndex" : 0,
					"id" : "Aud1.2::@6890427a1f51a3e7e1df",
					"jsonFile" : "target-Aud1.2-Debug-4bbfeec79c659c675492.json",
					"name" : "Aud1.2",
					"projectIndex" : 0
				},
				{
					"directoryIndex" : 0,
					"id" : "Aud10.1::@6890427a1f51a3e7e1df",
					"jsonFile" : "target-Aud10.1-Debug-e4060ce0adc0ab92169a.json",
					"name" : "Aud10.1",
					"projectIndex" : 0
				},
				{
					"directoryIndex" : 0,
					"id" : "Aud10.1.2::@6890427a1f51a3e7e1df",
					"jsonFile" : "target-Aud10.1.2-Debug-08b3bc16a30b59eacf85.json",
					"name" : "Aud10.1.2",
					"projectIndex" : 0
				},
				{
					"directoryIndex" : 0,
					"id" : "Aud10.2::@6890427a1f51a3e7e1df",
					"jsonFile" : "target-Aud10.2-Debug-1e2a4912375056091259.json",
					"name" : "Aud10.2",
					"projectIndex" : 0
				},
				{
					"directoryIndex" : 0,
					"id" : "Aud10.3::@6890427a1f51a3e7e1df",
					"jsonFile" : "target-Aud10.3-Debug-458d0a4efa6f5299f27b.json",
					"name" : "Aud10.3",
					"projectIndex" : 0
				},
				{
					"directoryIndex" : 0,
					"id" : "Aud10.4::@6890427a1f51a3e7e1df",
					"jsonFile" : "target-Aud10.4-Debug-5ac9826be97ce3b9f2a0.json",
					"name" : "Aud10.4",
					"projectIndex" : 0
				},
				{
					"directoryIndex" : 0,
					"id" : "Aud10.5::@6890427a1f51a3e7e1df",
					"jsonFile" : "target-Aud10.5-Debug-10a1a366b7332a45bdd6.json",
					"name" : "Aud10.5",
					"projectIndex" : 0
				},
				{
					"directoryIndex" : 0,
					"id" : "Aud10.6::@6890427a1f51a3e7e1df",
					"jsonFile" : "target-Aud10.6-Debug-08ab97f32a591a748be1.json",
					"name" : "Aud10.6",
					"projectIndex" : 0
				},
				{
					"directoryIndex" : 0,
					"id" : "Aud10.7::@6890427a1f51a3e7e1df",
					"jsonFile" : "target-Aud10.7-Debug-a4b793313f667a9ca25a.json",
					"name" : "Aud10.7",
					"projectIndex" : 0
				},
				{
					"directoryIndex" : 0,
					"id" : "Aud10.8::@6890427a1f51a3e7e1df",
					"jsonFile" : "target-Aud10.8-Debug-6afa0010e78e3f984bd8.json",
					"name" : "Aud10.8",
					"projectIndex" : 0
				},
				{
					"directoryIndex" : 0,
					"id" : "Aud2.1::@6890427a1f51a3e7e1df",
					"jsonFile" : "target-Aud2.1-Debug-8bba5522f6d8f2cca96a.json",
					"name" : "Aud2.1",
					"projectIndex" : 0
				},
				{
					"directoryIndex" : 0,
					"id" : "Aud2.10::@6890427a1f51a3e7e1df",
					"jsonFile" : "target-Aud2.10-Debug-b6388d1774a4f513c4b7.json",
					"name" : "Aud2.10",
					"projectIndex" : 0
				},
				{
					"directoryIndex" : 0,
					"id" : "Aud2.11::@6890427a1f51a3e7e1df",
					"jsonFile" : "target-Aud2.11-Debug-8e35988b1327efd07b4a.json",
					"name" : "Aud2.11",
					"projectIndex" : 0
				},
				{
					"directoryIndex" : 0,
					"id" : "Aud2.12::@6890427a1f51a3e7e1df",
					"jsonFile" : "target-Aud2.12-Debug-54c23eea34a326108bca.json",
					"name" : "Aud2.12",
					"projectIndex" : 0
				},
				{
					"directoryIndex" : 0,
					"id" : "Aud2.2::@6890427a1f51a3e7e1df",
					"jsonFile" : "target-Aud2.2-Debug-823a32c1eb64b50a253e.json",
					"name" : "Aud2.2",
					"projectIndex" : 0
				},
				{
					"directoryIndex" : 0,
					"id" : "Aud2.3::@6890427a1f51a3e7e1df",
					"jsonFile" : "target-Aud2.3-Debug-4f0e30abe13b16be3429.json",
					"name" : "Aud2.3",
					"projectIndex" : 0
				},
				{
					"directoryIndex" : 0,
					"id" : "Aud2.4::@6890427a1f51a3e7e1df",
					"jsonFile" : "target-Aud2.4-Debug-f2bd2909e5f9bd30ea74.json",
					"name" : "Aud2.4",
					"projectIndex" : 0
				},
				{
					"directoryIndex" : 0,
					"id" : "Aud2.5::@6890427a1f51a3e7e1df",
					"jsonFile" : "target-Aud2.5-Debug-298f6b01f6558449dc45.json",
					"name" : "Aud2.5",
					"projectIndex" : 0
				},
				{
					"directoryIndex" : 0,
					"id" : "Aud2.6::@6890427a1f51a3e7e1df",
					"jsonFile" : "target-Aud2.6-Debug-d5306b1c072679ea0586.json",
					"name" : "Aud2.6",
					"projectIndex" : 0
				},
				{
					"directoryIndex" : 0,
					"id" : "Aud2.7::@6890427a1f51a3e7e1df",
					"jsonFile" : "target-Aud2.7-Debug-6faf9b9a1f0a5e9330b4.json",
					"name" : "Aud2.7",
					"projectIndex" : 0
				},
				{
					"directoryIndex" : 0,
					"id" : "Aud2.8::@6890427a1f51a3e7e1df",
					"jsonFile" : "target-Aud2.8-Debug-73c60592e55eff34382d.json",
					"name" : "Aud2.8",
					"projectIndex" : 0
				},
				{
					"directoryIndex" : 0,
					"id" : "Aud2.9::@6890427a1f51a3e7e1df",
					"jsonFile" : "target-Aud2.9-Debug-429b252007051c4b9b4c.json",
					"name" : "Aud2.9",
					"projectIndex" : 0
				},
				{
					"directoryIndex" : 0,
					"id" : "Aud3.1::@6890427a1f51a3e7e1df",
					"jsonFile" : "target-Aud3.1-Debug-1adb8deb4e9e562ca968.json",
					"name" : "Aud3.1",
					"projectIndex" : 0
				},
				{
					"directoryIndex" : 0,
					"id" : "Aud3.2::@6890427a1f51a3e7e1df",
					"jsonFile" : "target-Aud3.2-Debug-c45ea8d1085c2998e983.json",
					"name" : "Aud3.2",
					"projectIndex" : 0
				},
				{
					"directoryIndex" : 0,
					"id" : "Aud3.2Bonus::@6890427a1f51a3e7e1df",
					"jsonFile" : "target-Aud3.2Bonus-Debug-5ae536ab446fc7dcd825.json",
					"name" : "Aud3.2Bonus",
					"projectIndex" : 0
				},
				{
					"directoryIndex" : 0,
					"id" : "Aud3.2Spoeno::@6890427a1f51a3e7e1df",
					"jsonFile" : "target-Aud3.2Spoeno-Debug-f25ce52a46e80631f972.json",
					"name" : "Aud3.2Spoeno",
					"projectIndex" : 0
				},
				{
					"directoryIndex" : 0,
					"id" : "Aud3.3::@6890427a1f51a3e7e1df",
					"jsonFile" : "target-Aud3.3-Debug-bde23f51511854e1ab0e.json",
					"name" : "Aud3.3",
					"projectIndex" : 0
				},
				{
					"directoryIndex" : 0,
					"id" : "Aud3.4::@6890427a1f51a3e7e1df",
					"jsonFile" : "target-Aud3.4-Debug-73140550276c51767d82.json",
					"name" : "Aud3.4",
					"projectIndex" : 0
				},
				{
					"directoryIndex" : 0,
					"id" : "Aud3.5::@6890427a1f51a3e7e1df",
					"jsonFile" : "target-Aud3.5-Debug-47e9d5c052016c907862.json",
					"name" : "Aud3.5",
					"projectIndex" : 0
				},
				{
					"directoryIndex" : 0,
					"id" : "Aud3.6::@6890427a1f51a3e7e1df",
					"jsonFile" : "target-Aud3.6-Debug-403e8d6360a38e93778b.json",
					"name" : "Aud3.6",
					"projectIndex" : 0
				},
				{
					"directoryIndex" : 0,
					"id" : "Aud3.7::@6890427a1f51a3e7e1df",
					"jsonFile" : "target-Aud3.7-Debug-84128dce9b6a00758916.json",
					"name" : "Aud3.7",
					"projectIndex" : 0
				},
				{
					"directoryIndex" : 0,
					"id" : "Aud3.8.1::@6890427a1f51a3e7e1df",
					"jsonFile" : "target-Aud3.8.1-Debug-47ae0a2f1ff8805c3f6f.json",
					"name" : "Aud3.8.1",
					"projectIndex" : 0
				},
				{
					"directoryIndex" : 0,
					"id" : "Aud3.8.2::@6890427a1f51a3e7e1df",
					"jsonFile" : "target-Aud3.8.2-Debug-0f0ee93ac29f458ae942.json",
					"name" : "Aud3.8.2",
					"projectIndex" : 0
				},
				{
					"directoryIndex" : 0,
					"id" : "Aud3.9::@6890427a1f51a3e7e1df",
					"jsonFile" : "target-Aud3.9-Debug-5b88c4716ca71c1e9ab4.json",
					"name" : "Aud3.9",
					"projectIndex" : 0
				},
				{
					"directoryIndex" : 0,
					"id" : "Aud4.1.1::@6890427a1f51a3e7e1df",
					"jsonFile" : "target-Aud4.1.1-Debug-ac71537f378b516c988a.json",
					"name" : "Aud4.1.1",
					"projectIndex" : 0
				},
				{
					"directoryIndex" : 0,
					"id" : "Aud4.1.2::@6890427a1f51a3e7e1df",
					"jsonFile" : "target-Aud4.1.2-Debug-8eeafd41541c24cd013a.json",
					"name" : "Aud4.1.2",
					"projectIndex" : 0
				},
				{
					"directoryIndex" : 0,
					"id" : "Aud4.1.3::@6890427a1f51a3e7e1df",
					"jsonFile" : "target-Aud4.1.3-Debug-8b8bbde1281c1cb14997.json",
					"name" : "Aud4.1.3",
					"projectIndex" : 0
				},
				{
					"directoryIndex" : 0,
					"id" : "Aud4.10::@6890427a1f51a3e7e1df",
					"jsonFile" : "target-Aud4.10-Debug-c0c96d692d3014217196.json",
					"name" : "Aud4.10",
					"projectIndex" : 0
				},
				{
					"directoryIndex" : 0,
					"id" : "Aud4.11::@6890427a1f51a3e7e1df",
					"jsonFile" : "target-Aud4.11-Debug-a87dc25381eef8f211c1.json",
					"name" : "Aud4.11",
					"projectIndex" : 0
				},
				{
					"directoryIndex" : 0,
					"id" : "Aud4.2.1::@6890427a1f51a3e7e1df",
					"jsonFile" : "target-Aud4.2.1-Debug-9bb40553c4488ca2eb52.json",
					"name" : "Aud4.2.1",
					"projectIndex" : 0
				},
				{
					"directoryIndex" : 0,
					"id" : "Aud4.2.2::@6890427a1f51a3e7e1df",
					"jsonFile" : "target-Aud4.2.2-Debug-0f017bf3dde7016e23ba.json",
					"name" : "Aud4.2.2",
					"projectIndex" : 0
				},
				{
					"directoryIndex" : 0,
					"id" : "Aud4.2.3::@6890427a1f51a3e7e1df",
					"jsonFile" : "target-Aud4.2.3-Debug-5ebb46e76ff3282df8d3.json",
					"name" : "Aud4.2.3",
					"projectIndex" : 0
				},
				{
					"directoryIndex" : 0,
					"id" : "Aud4.3::@6890427a1f51a3e7e1df",
					"jsonFile" : "target-Aud4.3-Debug-c0cb1cf42cc33837ad1c.json",
					"name" : "Aud4.3",
					"projectIndex" : 0
				},
				{
					"directoryIndex" : 0,
					"id" : "Aud4.4::@6890427a1f51a3e7e1df",
					"jsonFile" : "target-Aud4.4-Debug-bbfa394aa2a5df5d2d25.json",
					"name" : "Aud4.4",
					"projectIndex" : 0
				},
				{
					"directoryIndex" : 0,
					"id" : "Aud4.5::@6890427a1f51a3e7e1df",
					"jsonFile" : "target-Aud4.5-Debug-92c28150a4277d13ad65.json",
					"name" : "Aud4.5",
					"projectIndex" : 0
				},
				{
					"directoryIndex" : 0,
					"id" : "Aud4.6::@6890427a1f51a3e7e1df",
					"jsonFile" : "target-Aud4.6-Debug-85dbb7da6ba36975b3d9.json",
					"name" : "Aud4.6",
					"projectIndex" : 0
				},
				{
					"directoryIndex" : 0,
					"id" : "Aud4.8::@6890427a1f51a3e7e1df",
					"jsonFile" : "target-Aud4.8-Debug-af9f9b97aed0d5e30d99.json",
					"name" : "Aud4.8",
					"projectIndex" : 0
				},
				{
					"directoryIndex" : 0,
					"id" : "Aud4.9::@6890427a1f51a3e7e1df",
					"jsonFile" : "target-Aud4.9-Debug-640db7ad1d2100767ae5.json",
					"name" : "Aud4.9",
					"projectIndex" : 0
				},
				{
					"directoryIndex" : 0,
					"id" : "Aud5.1::@6890427a1f51a3e7e1df",
					"jsonFile" : "target-Aud5.1-Debug-b667f133fecbdc36d2c0.json",
					"name" : "Aud5.1",
					"projectIndex" : 0
				},
				{
					"directoryIndex" : 0,
					"id" : "Aud5.10::@6890427a1f51a3e7e1df",
					"jsonFile" : "target-Aud5.10-Debug-a6e5061e274c10c0d187.json",
					"name" : "Aud5.10",
					"projectIndex" : 0
				},
				{
					"directoryIndex" : 0,
					"id" : "Aud5.11::@6890427a1f51a3e7e1df",
					"jsonFile" : "target-Aud5.11-Debug-bacce5bbd067c5018b85.json",
					"name" : "Aud5.11",
					"projectIndex" : 0
				},
				{
					"directoryIndex" : 0,
					"id" : "Aud5.12::@6890427a1f51a3e7e1df",
					"jsonFile" : "target-Aud5.12-Debug-439a17c5a09c8f2c622f.json",
					"name" : "Aud5.12",
					"projectIndex" : 0
				},
				{
					"directoryIndex" : 0,
					"id" : "Aud5.13::@6890427a1f51a3e7e1df",
					"jsonFile" : "target-Aud5.13-Debug-2de59295b2efc2f29291.json",
					"name" : "Aud5.13",
					"projectIndex" : 0
				},
				{
					"directoryIndex" : 0,
					"id" : "Aud5.14::@6890427a1f51a3e7e1df",
					"jsonFile" : "target-Aud5.14-Debug-1be23579fc5723d289b2.json",
					"name" : "Aud5.14",
					"projectIndex" : 0
				},
				{
					"directoryIndex" : 0,
					"id" : "Aud5.15.1::@6890427a1f51a3e7e1df",
					"jsonFile" : "target-Aud5.15.1-Debug-b0aab029a3f8ffc01c32.json",
					"name" : "Aud5.15.1",
					"projectIndex" : 0
				},
				{
					"directoryIndex" : 0,
					"id" : "Aud5.15.2::@6890427a1f51a3e7e1df",
					"jsonFile" : "target-Aud5.15.2-Debug-304ec2b3165c7dabbfdd.json",
					"name" : "Aud5.15.2",
					"projectIndex" : 0
				},
				{
					"directoryIndex" : 0,
					"id" : "Aud5.2.1::@6890427a1f51a3e7e1df",
					"jsonFile" : "target-Aud5.2.1-Debug-c3a196404585f431b0e0.json",
					"name" : "Aud5.2.1",
					"projectIndex" : 0
				},
				{
					"directoryIndex" : 0,
					"id" : "Aud5.2.2::@6890427a1f51a3e7e1df",
					"jsonFile" : "target-Aud5.2.2-Debug-dbef133a4047d4c07e1a.json",
					"name" : "Aud5.2.2",
					"projectIndex" : 0
				},
				{
					"directoryIndex" : 0,
					"id" : "Aud5.3.1::@6890427a1f51a3e7e1df",
					"jsonFile" : "target-Aud5.3.1-Debug-88e39da720168546bc43.json",
					"name" : "Aud5.3.1",
					"projectIndex" : 0
				},
				{
					"directoryIndex" : 0,
					"id" : "Aud5.3.2::@6890427a1f51a3e7e1df",
					"jsonFile" : "target-Aud5.3.2-Debug-cf5cf1c2661f3f8db296.json",
					"name" : "Aud5.3.2",
					"projectIndex" : 0
				},
				{
					"directoryIndex" : 0,
					"id" : "Aud5.3.3::@6890427a1f51a3e7e1df",
					"jsonFile" : "target-Aud5.3.3-Debug-9a0e34d47d97893a5473.json",
					"name" : "Aud5.3.3",
					"projectIndex" : 0
				},
				{
					"directoryIndex" : 0,
					"id" : "Aud5.3.4::@6890427a1f51a3e7e1df",
					"jsonFile" : "target-Aud5.3.4-Debug-1a8546c3836e31ed6e12.json",
					"name" : "Aud5.3.4",
					"projectIndex" : 0
				},
				{
					"directoryIndex" : 0,
					"id" : "Aud5.4.1::@6890427a1f51a3e7e1df",
					"jsonFile" : "target-Aud5.4.1-Debug-7988f24399d638c261a7.json",
					"name" : "Aud5.4.1",
					"projectIndex" : 0
				},
				{
					"directoryIndex" : 0,
					"id" : "Aud5.4.2::@6890427a1f51a3e7e1df",
					"jsonFile" : "target-Aud5.4.2-Debug-2363d0873d27e1f6f0b8.json",
					"name" : "Aud5.4.2",
					"projectIndex" : 0
				},
				{
					"directoryIndex" : 0,
					"id" : "Aud5.4.3::@6890427a1f51a3e7e1df",
					"jsonFile" : "target-Aud5.4.3-Debug-c65830617a6a295866cb.json",
					"name" : "Aud5.4.3",
					"projectIndex" : 0
				},
				{
					"directoryIndex" : 0,
					"id" : "Aud5.5::@6890427a1f51a3e7e1df",
					"jsonFile" : "target-Aud5.5-Debug-97b7585b5e23f55ef2aa.json",
					"name" : "Aud5.5",
					"projectIndex" : 0
				},
				{
					"directoryIndex" : 0,
					"id" : "Aud5.5.2::@6890427a1f51a3e7e1df",
					"jsonFile" : "target-Aud5.5.2-Debug-115fefafacf629602776.json",
					"name" : "Aud5.5.2",
					"projectIndex" : 0
				},
				{
					"directoryIndex" : 0,
					"id" : "Aud5.6::@6890427a1f51a3e7e1df",
					"jsonFile" : "target-Aud5.6-Debug-51b9524c2073083b0f92.json",
					"name" : "Aud5.6",
					"projectIndex" : 0
				},
				{
					"directoryIndex" : 0,
					"id" : "Aud5.6.2::@6890427a1f51a3e7e1df",
					"jsonFile" : "target-Aud5.6.2-Debug-343d311968c3126326bc.json",
					"name" : "Aud5.6.2",
					"projectIndex" : 0
				},
				{
					"directoryIndex" : 0,
					"id" : "Aud5.7::@6890427a1f51a3e7e1df",
					"jsonFile" : "target-Aud5.7-Debug-d51c0d1f43bedb667016.json",
					"name" : "Aud5.7",
					"projectIndex" : 0
				},
				{
					"directoryIndex" : 0,
					"id" : "Aud5.8::@6890427a1f51a3e7e1df",
					"jsonFile" : "target-Aud5.8-Debug-5c09996229701bf39e28.json",
					"name" : "Aud5.8",
					"projectIndex" : 0
				},
				{
					"directoryIndex" : 0,
					"id" : "Aud5.9::@6890427a1f51a3e7e1df",
					"jsonFile" : "target-Aud5.9-Debug-62e2a2d93016f9e571e6.json",
					"name" : "Aud5.9",
					"projectIndex" : 0
				},
				{
					"directoryIndex" : 0,
					"id" : "Aud6.1::@6890427a1f51a3e7e1df",
					"jsonFile" : "target-Aud6.1-Debug-2b270fd25c217a70bd67.json",
					"name" : "Aud6.1",
					"projectIndex" : 0
				},
				{
					"directoryIndex" : 0,
					"id" : "Aud6.2::@6890427a1f51a3e7e1df",
					"jsonFile" : "target-Aud6.2-Debug-51124576e65d347cd5a0.json",
					"name" : "Aud6.2",
					"projectIndex" : 0
				},
				{
					"directoryIndex" : 0,
					"id" : "Aud6.3::@6890427a1f51a3e7e1df",
					"jsonFile" : "target-Aud6.3-Debug-94d234a137f295e12813.json",
					"name" : "Aud6.3",
					"projectIndex" : 0
				},
				{
					"directoryIndex" : 0,
					"id" : "Aud6.4::@6890427a1f51a3e7e1df",
					"jsonFile" : "target-Aud6.4-Debug-67ec74e477a692b7e096.json",
					"name" : "Aud6.4",
					"projectIndex" : 0
				},
				{
					"directoryIndex" : 0,
					"id" : "Aud6.4.2::@6890427a1f51a3e7e1df",
					"jsonFile" : "target-Aud6.4.2-Debug-bc3610828dfbcc12c3be.json",
					"name" : "Aud6.4.2",
					"projectIndex" : 0
				},
				{
					"directoryIndex" : 0,
					"id" : "Aud6.5::@6890427a1f51a3e7e1df",
					"jsonFile" : "target-Aud6.5-Debug-59f4089956bd330c8406.json",
					"name" : "Aud6.5",
					"projectIndex" : 0
				},
				{
					"directoryIndex" : 0,
					"id" : "Aud6.5.2::@6890427a1f51a3e7e1df",
					"jsonFile" : "target-Aud6.5.2-Debug-8b9db6f5da539d1a90db.json",
					"name" : "Aud6.5.2",
					"projectIndex" : 0
				},
				{
					"directoryIndex" : 0,
					"id" : "Aud6.6::@6890427a1f51a3e7e1df",
					"jsonFile" : "target-Aud6.6-Debug-928c5937e9ddfbacd740.json",
					"name" : "Aud6.6",
					"projectIndex" : 0
				},
				{
					"directoryIndex" : 0,
					"id" : "Aud6.7::@6890427a1f51a3e7e1df",
					"jsonFile" : "target-Aud6.7-Debug-da1a78f0a60da4ffa63f.json",
					"name" : "Aud6.7",
					"projectIndex" : 0
				},
				{
					"directoryIndex" : 0,
					"id" : "Aud6.8::@6890427a1f51a3e7e1df",
					"jsonFile" : "target-Aud6.8-Debug-3c30a5a28c3dc20d94b8.json",
					"name" : "Aud6.8",
					"projectIndex" : 0
				},
				{
					"directoryIndex" : 0,
					"id" : "Aud6.8.2::@6890427a1f51a3e7e1df",
					"jsonFile" : "target-Aud6.8.2-Debug-1736c7608cf4b0deb8ba.json",
					"name" : "Aud6.8.2",
					"projectIndex" : 0
				},
				{
					"directoryIndex" : 0,
					"id" : "Aud7.1::@6890427a1f51a3e7e1df",
					"jsonFile" : "target-Aud7.1-Debug-2873148f6cc33283c910.json",
					"name" : "Aud7.1",
					"projectIndex" : 0
				},
				{
					"directoryIndex" : 0,
					"id" : "Aud7.10::@6890427a1f51a3e7e1df",
					"jsonFile" : "target-Aud7.10-Debug-2e7aaddd8e20c346d51a.json",
					"name" : "Aud7.10",
					"projectIndex" : 0
				},
				{
					"directoryIndex" : 0,
					"id" : "Aud7.2::@6890427a1f51a3e7e1df",
					"jsonFile" : "target-Aud7.2-Debug-6d05faa9b914d5c5e0f3.json",
					"name" : "Aud7.2",
					"projectIndex" : 0
				},
				{
					"directoryIndex" : 0,
					"id" : "Aud7.3::@6890427a1f51a3e7e1df",
					"jsonFile" : "target-Aud7.3-Debug-29e49d7afeba05cf30dd.json",
					"name" : "Aud7.3",
					"projectIndex" : 0
				},
				{
					"directoryIndex" : 0,
					"id" : "Aud7.4::@6890427a1f51a3e7e1df",
					"jsonFile" : "target-Aud7.4-Debug-c4f8bb46f8dd193aaaf9.json",
					"name" : "Aud7.4",
					"projectIndex" : 0
				},
				{
					"directoryIndex" : 0,
					"id" : "Aud7.5::@6890427a1f51a3e7e1df",
					"jsonFile" : "target-Aud7.5-Debug-52814bcc2e79c6cbd390.json",
					"name" : "Aud7.5",
					"projectIndex" : 0
				},
				{
					"directoryIndex" : 0,
					"id" : "Aud7.6::@6890427a1f51a3e7e1df",
					"jsonFile" : "target-Aud7.6-Debug-74c4fa1f89b251b75a03.json",
					"name" : "Aud7.6",
					"projectIndex" : 0
				},
				{
					"directoryIndex" : 0,
					"id" : "Aud7.7::@6890427a1f51a3e7e1df",
					"jsonFile" : "target-Aud7.7-Debug-3a298ed4e2262e0df7be.json",
					"name" : "Aud7.7",
					"projectIndex" : 0
				},
				{
					"directoryIndex" : 0,
					"id" : "Aud7.8::@6890427a1f51a3e7e1df",
					"jsonFile" : "target-Aud7.8-Debug-cf730b1923e22ff808c5.json",
					"name" : "Aud7.8",
					"projectIndex" : 0
				},
				{
					"directoryIndex" : 0,
					"id" : "Aud7.9::@6890427a1f51a3e7e1df",
					"jsonFile" : "target-Aud7.9-Debug-687dc268ef2927f2ee82.json",
					"name" : "Aud7.9",
					"projectIndex" : 0
				},
				{
					"directoryIndex" : 0,
					"id" : "Aud8.1::@6890427a1f51a3e7e1df",
					"jsonFile" : "target-Aud8.1-Debug-415df7bda69caa5d08da.json",
					"name" : "Aud8.1",
					"projectIndex" : 0
				},
				{
					"directoryIndex" : 0,
					"id" : "Aud8.1.2::@6890427a1f51a3e7e1df",
					"jsonFile" : "target-Aud8.1.2-Debug-9dd81e7bcb03b2489648.json",
					"name" : "Aud8.1.2",
					"projectIndex" : 0
				},
				{
					"directoryIndex" : 0,
					"id" : "Aud8.1.3::@6890427a1f51a3e7e1df",
					"jsonFile" : "target-Aud8.1.3-Debug-254655629c6e39d1d993.json",
					"name" : "Aud8.1.3",
					"projectIndex" : 0
				},
				{
					"directoryIndex" : 0,
					"id" : "Aud8.2::@6890427a1f51a3e7e1df",
					"jsonFile" : "target-Aud8.2-Debug-1669582a71ebf7e42749.json",
					"name" : "Aud8.2",
					"projectIndex" : 0
				},
				{
					"directoryIndex" : 0,
					"id" : "Aud8.2.2::@6890427a1f51a3e7e1df",
					"jsonFile" : "target-Aud8.2.2-Debug-4d46c7e399c0ad3bd1e6.json",
					"name" : "Aud8.2.2",
					"projectIndex" : 0
				},
				{
					"directoryIndex" : 0,
					"id" : "Aud8.3::@6890427a1f51a3e7e1df",
					"jsonFile" : "target-Aud8.3-Debug-0a5b87f3e7c1f0900421.json",
					"name" : "Aud8.3",
					"projectIndex" : 0
				},
				{
					"directoryIndex" : 0,
					"id" : "Aud8.3.2::@6890427a1f51a3e7e1df",
					"jsonFile" : "target-Aud8.3.2-Debug-b257cd977409355a44ab.json",
					"name" : "Aud8.3.2",
					"projectIndex" : 0
				},
				{
					"directoryIndex" : 0,
					"id" : "Aud8.4::@6890427a1f51a3e7e1df",
					"jsonFile" : "target-Aud8.4-Debug-a74589144042955f21a7.json",
					"name" : "Aud8.4",
					"projectIndex" : 0
				},
				{
					"directoryIndex" : 0,
					"id" : "Aud8.5::@6890427a1f51a3e7e1df",
					"jsonFile" : "target-Aud8.5-Debug-a3adde108cf0e75c27a7.json",
					"name" : "Aud8.5",
					"projectIndex" : 0
				},
				{
					"directoryIndex" : 0,
					"id" : "Aud9.1::@6890427a1f51a3e7e1df",
					"jsonFile" : "target-Aud9.1-Debug-90f33cd1cadedff13705.json",
					"name" : "Aud9.1",
					"projectIndex" : 0
				},
				{
					"directoryIndex" : 0,
					"id" : "Aud9.1.2::@6890427a1f51a3e7e1df",
					"jsonFile" : "target-Aud9.1.2-Debug-83e3183f51e6a36c302d.json",
					"name" : "Aud9.1.2",
					"projectIndex" : 0
				},
				{
					"directoryIndex" : 0,
					"id" : "Aud9.2::@6890427a1f51a3e7e1df",
					"jsonFile" : "target-Aud9.2-Debug-2d15ef7c201627787097.json",
					"name" : "Aud9.2",
					"projectIndex" : 0
				},
				{
					"directoryIndex" : 0,
					"id" : "Aud9.3::@6890427a1f51a3e7e1df",
					"jsonFile" : "target-Aud9.3-Debug-10ee5daef0fe6ddac5fe.json",
					"name" : "Aud9.3",
					"projectIndex" : 0
				},
				{
					"directoryIndex" : 0,
					"id" : "Aud9.3.2::@6890427a1f51a3e7e1df",
					"jsonFile" : "target-Aud9.3.2-Debug-fb189d0f7a79c4918587.json",
					"name" : "Aud9.3.2",
					"projectIndex" : 0
				},
				{
					"directoryIndex" : 0,
					"id" : "Aud9.4::@6890427a1f51a3e7e1df",
					"jsonFile" : "target-Aud9.4-Debug-62ccfcdee0fc4b8bbdd8.json",
					"name" : "Aud9.4",
					"projectIndex" : 0
				},
				{
					"directoryIndex" : 0,
					"id" : "Aud9.5::@6890427a1f51a3e7e1df",
					"jsonFile" : "target-Aud9.5-Debug-a5717a91470dc8f47ab3.json",
					"name" : "Aud9.5",
					"projectIndex" : 0
				},
				{
					"directoryIndex" : 0,
					"id" : "Aud9.6::@6890427a1f51a3e7e1df",
					"jsonFile" : "target-Aud9.6-Debug-cfdc786148e403c1101a.json",
					"name" : "Aud9.6",
					"projectIndex" : 0
				},
				{
					"directoryIndex" : 0,
					"id" : "Aud9.7::@6890427a1f51a3e7e1df",
					"jsonFile" : "target-Aud9.7-Debug-f5b07e9fb3e52e04341e.json",
					"name" : "Aud9.7",
					"projectIndex" : 0
				},
				{
					"directoryIndex" : 0,
					"id" : "Bingo::@6890427a1f51a3e7e1df",
					"jsonFile" : "target-Bingo-Debug-a06752615d9d16f91d4e.json",
					"name" : "Bingo",
					"projectIndex" : 0
				},
				{
					"directoryIndex" : 0,
					"id" : "BrDeliteliCifrBr::@6890427a1f51a3e7e1df",
					"jsonFile" : "target-BrDeliteliCifrBr-Debug-045de37cca0d6c53589b.json",
					"name" : "BrDeliteliCifrBr",
					"projectIndex" : 0
				},
				{
					"directoryIndex" : 0,
					"id" : "BrojCifri::@6890427a1f51a3e7e1df",
					"jsonFile" : "target-BrojCifri-Debug-d1bbc6e750a397df751f.json",
					"name" : "BrojCifri",
					"projectIndex" : 0
				},
				{
					"directoryIndex" : 0,
					"id" : "BrojCifriX::@6890427a1f51a3e7e1df",
					"jsonFile" : "target-BrojCifriX-Debug-6d8a29f51c2c5bf1165c.json",
					"name" : "BrojCifriX",
					"projectIndex" : 0
				},
				{
					"directoryIndex" : 0,
					"id" : "Brojanica::@6890427a1f51a3e7e1df",
					"jsonFile" : "target-Brojanica-Debug-91a366c23b4ac0ea001e.json",
					"name" : "Brojanica",
					"projectIndex" : 0
				},
				{
					"directoryIndex" : 0,
					"id" : "Carina::@6890427a1f51a3e7e1df",
					"jsonFile" : "target-Carina-Debug-7b272816c361cbcb6d26.json",
					"name" : "Carina",
					"projectIndex" : 0
				},
				{
					"directoryIndex" : 0,
					"id" : "CitajMatrica::@6890427a1f51a3e7e1df",
					"jsonFile" : "target-CitajMatrica-Debug-92249f1d58f55e29f87a.json",
					"name" : "CitajMatrica",
					"projectIndex" : 0
				},
				{
					"directoryIndex" : 0,
					"id" : "DeliviParniDeliviNeparni::@6890427a1f51a3e7e1df",
					"jsonFile" : "target-DeliviParniDeliviNeparni-Debug-d801bcdc3766755cbeb1.json",
					"name" : "DeliviParniDeliviNeparni",
					"projectIndex" : 0
				},
				{
					"directoryIndex" : 0,
					"id" : "Dijagonali::@6890427a1f51a3e7e1df",
					"jsonFile" : "target-Dijagonali-Debug-5a0bd0cc1ae6679bcdbc.json",
					"name" : "Dijagonali",
					"projectIndex" : 0
				},
				{
					"directoryIndex" : 0,
					"id" : "DijagonalnoPecatenje::@6890427a1f51a3e7e1df",
					"jsonFile" : "target-DijagonalnoPecatenje-Debug-21e61a58c315c5914e0c.json",
					"name" : "DijagonalnoPecatenje",
					"projectIndex" : 0
				},
				{
					"directoryIndex" : 0,
					"id" : "DiplenjeZadaca::@6890427a1f51a3e7e1df",
					"jsonFile" : "target-DiplenjeZadaca-Debug-3a2b5ec62f64dfa044b4.json",
					"name" : "DiplenjeZadaca",
					"projectIndex" : 0
				},
				{
					"directoryIndex" : 0,
					"id" : "DodavanjeNiza::@6890427a1f51a3e7e1df",
					"jsonFile" : "target-DodavanjeNiza-Debug-d3e224a36cf6c4838ab7.json",
					"name" : "DodavanjeNiza",
					"projectIndex" : 0
				},
				{
					"directoryIndex" : 0,
					"id" : "Domasno1::@6890427a1f51a3e7e1df",
					"jsonFile" : "target-Domasno1-Debug-28713b27cd1dcba901a2.json",
					"name" : "Domasno1",
					"projectIndex" : 0
				},
				{
					"directoryIndex" : 0,
					"id" : "Domasno10.9::@6890427a1f51a3e7e1df",
					"jsonFile" : "target-Domasno10.9-Debug-a76f305617f59285400b.json",
					"name" : "Domasno10.9",
					"projectIndex" : 0
				},
				{
					"directoryIndex" : 0,
					"id" : "Domasno2::@6890427a1f51a3e7e1df",
					"jsonFile" : "target-Domasno2-Debug-9192563f5c5be167ec91.json",
					"name" : "Domasno2",
					"projectIndex" : 0
				},
				{
					"directoryIndex" : 0,
					"id" : "Domasno7.10::@6890427a1f51a3e7e1df",
					"jsonFile" : "target-Domasno7.10-Debug-40c0e46e0bf969cbe5db.json",
					"name" : "Domasno7.10",
					"projectIndex" : 0
				},
				{
					"directoryIndex" : 0,
					"id" : "Domasno9.8::@6890427a1f51a3e7e1df",
					"jsonFile" : "target-Domasno9.8-Debug-276fcbe5ccda17063cda.json",
					"name" : "Domasno9.8",
					"projectIndex" : 0
				},
				{
					"directoryIndex" : 0,
					"id" : "Domasno9.9::@6890427a1f51a3e7e1df",
					"jsonFile" : "target-Domasno9.9-Debug-31c659cae2c498882bec.json",
					"name" : "Domasno9.9",
					"projectIndex" : 0
				},
				{
					"directoryIndex" : 0,
					"id" : "DrzavaX::@6890427a1f51a3e7e1df",
					"jsonFile" : "target-DrzavaX-Debug-9579596bd2958dada817.json",
					"name" : "DrzavaX",
					"projectIndex" : 0
				},
				{
					"directoryIndex" : 0,
					"id" : "Ednakvost2Broja::@6890427a1f51a3e7e1df",
					"jsonFile" : "target-Ednakvost2Broja-Debug-48e410343a749f402aba.json",
					"name" : "Ednakvost2Broja",
					"projectIndex" : 0
				},
				{
					"directoryIndex" : 0,
					"id" : "Elka::@6890427a1f51a3e7e1df",
					"jsonFile" : "target-Elka-Debug-d162a2629bf1743a470c.json",
					"name" : "Elka",
					"projectIndex" : 0
				},
				{
					"directoryIndex" : 0,
					"id" : "FILM_TEKSA::@6890427a1f51a3e7e1df",
					"jsonFile" : "target-FILM_TEKSA-Debug-20ea3fc7441919beb14c.json",
					"name" : "FILM_TEKSA",
					"projectIndex" : 0
				},
				{
					"directoryIndex" : 0,
					"id" : "FINKIPoker::@6890427a1f51a3e7e1df",
					"jsonFile" : "target-FINKIPoker-Debug-409527ffe41675fda1f4.json",
					"name" : "FINKIPoker",
					"projectIndex" : 0
				},
				{
					"directoryIndex" : 0,
					"id" : "Factoriel::@6890427a1f51a3e7e1df",
					"jsonFile" : "target-Factoriel-Debug-2768626150ce729a57a5.json",
					"name" : "Factoriel",
					"projectIndex" : 0
				},
				{
					"directoryIndex" : 0,
					"id" : "FiskalniSmetki::@6890427a1f51a3e7e1df",
					"jsonFile" : "target-FiskalniSmetki-Debug-b4a12d51957dac5fed1f.json",
					"name" : "FiskalniSmetki",
					"projectIndex" : 0
				},
				{
					"directoryIndex" : 0,
					"id" : "Glusec::@6890427a1f51a3e7e1df",
					"jsonFile" : "target-Glusec-Debug-26e02c1df06519a7b9ba.json",
					"name" : "Glusec",
					"projectIndex" : 0
				},
				{
					"directoryIndex" : 0,
					"id" : "GodinaPresmetkiNacin1::@6890427a1f51a3e7e1df",
					"jsonFile" : "target-GodinaPresmetkiNacin1-Debug-8a209d6895827412b996.json",
					"name" : "GodinaPresmetkiNacin1",
					"projectIndex" : 0
				},
				{
					"directoryIndex" : 0,
					"id" : "GodinaPresmetkiNacin2::@6890427a1f51a3e7e1df",
					"jsonFile" : "target-GodinaPresmetkiNacin2-Debug-4ec0d9f7146a4a454e14.json",
					"name" : "GodinaPresmetkiNacin2",
					"projectIndex" : 0
				},
				{
					"directoryIndex" : 0,
					"id" : "HelloWorld::@6890427a1f51a3e7e1df",
					"jsonFile" : "target-HelloWorld-Debug-5f850f6beb9488068c75.json",
					"name" : "HelloWorld",
					"projectIndex" : 0
				},
				{
					"directoryIndex" : 0,
					"id" : "InteresenBroj::@6890427a1f51a3e7e1df",
					"jsonFile" : "target-InteresenBroj-Debug-5018bb15a4ab11ef28d5.json",
					"name" : "InteresenBroj",
					"projectIndex" : 0
				},
				{
					"directoryIndex" : 0,
					"id" : "IstiNizi::@6890427a1f51a3e7e1df",
					"jsonFile" : "target-IstiNizi-Debug-86f31523340790c7f6de.json",
					"name" : "IstiNizi",
					"projectIndex" : 0
				},
				{
					"directoryIndex" : 0,
					"id" : "Kalkulator::@6890427a1f51a3e7e1df",
					"jsonFile" : "target-Kalkulator-Debug-e4288a2b9f9bc673e913.json",
					"name" : "Kalkulator",
					"projectIndex" : 0
				},
				{
					"directoryIndex" : 0,
					"id" : "KinoKategorii::@6890427a1f51a3e7e1df",
					"jsonFile" : "target-KinoKategorii-Debug-22e5bd07d110933eadf4.json",
					"name" : "KinoKategorii",
					"projectIndex" : 0
				},
				{
					"directoryIndex" : 0,
					"id" : "Kombinacija3Broja::@6890427a1f51a3e7e1df",
					"jsonFile" : "target-Kombinacija3Broja-Debug-b705b6e53b8b89ff1768.json",
					"name" : "Kombinacija3Broja",
					"projectIndex" : 0
				},
				{
					"directoryIndex" : 0,
					"id" : "KoordPravoagolnik::@6890427a1f51a3e7e1df",
					"jsonFile" : "target-KoordPravoagolnik-Debug-b1ad2b1581699db6b8f5.json",
					"name" : "KoordPravoagolnik",
					"projectIndex" : 0
				},
				{
					"directoryIndex" : 0,
					"id" : "Kval1::@6890427a1f51a3e7e1df",
					"jsonFile" : "target-Kval1-Debug-04775c86606ca0997777.json",
					"name" : "Kval1",
					"projectIndex" : 0
				},
				{
					"directoryIndex" : 0,
					"id" : "KvoN::@6890427a1f51a3e7e1df",
					"jsonFile" : "target-KvoN-Debug-08faba84b36e7c368b68.json",
					"name" : "KvoN",
					"projectIndex" : 0
				},
				{
					"directoryIndex" : 0,
					"id" : "LabsAud1::@6890427a1f51a3e7e1df",
					"jsonFile" : "target-LabsAud1-Debug-3dfaf537e40ff54728a2.json",
					"name" : "LabsAud1",
					"projectIndex" : 0
				},
				{
					"directoryIndex" : 0,
					"id" : "LabsAud2::@6890427a1f51a3e7e1df",
					"jsonFile" : "target-LabsAud2-Debug-7289436d23e031c46b6c.json",
					"name" : "LabsAud2",
					"projectIndex" : 0
				},
				{
					"directoryIndex" : 0,
					"id" : "LabsSreda1::@6890427a1f51a3e7e1df",
					"jsonFile" : "target-LabsSreda1-Debug-2ab4de948e80b6115a22.json",
					"name" : "LabsSreda1",
					"projectIndex" : 0
				},
				{
					"directoryIndex" : 0,
					"id" : "LabsSreda2::@6890427a1f51a3e7e1df",
					"jsonFile" : "target-LabsSreda2-Debug-0e958f187277c5cd71dd.json",
					"name" : "LabsSreda2",
					"projectIndex" : 0
				},
				{
					"directoryIndex" : 0,
					"id" : "MagicnaMatrica::@6890427a1f51a3e7e1df",
					"jsonFile" : "target-MagicnaMatrica-Debug-5c0f5981c005b43189ee.json",
					"name" : "MagicnaMatrica",
					"projectIndex" : 0
				},
				{
					"directoryIndex" : 0,
					"id" : "Matrica1::@6890427a1f51a3e7e1df",
					"jsonFile" : "target-Matrica1-Debug-2384d7a269b333cde7b7.json",
					"name" : "Matrica1",
					"projectIndex" : 0
				},
				{
					"directoryIndex" : 0,
					"id" : "Matrica2::@6890427a1f51a3e7e1df",
					"jsonFile" : "target-Matrica2-Debug-14cada7b1a965566823f.json",
					"name" : "Matrica2",
					"projectIndex" : 0
				},
				{
					"directoryIndex" : 0,
					"id" : "Matrica3::@6890427a1f51a3e7e1df",
					"jsonFile" : "target-Matrica3-Debug-dfa5b3f3801789396b69.json",
					"name" : "Matrica3",
					"projectIndex" : 0
				},
				{
					"directoryIndex" : 0,
					"id" : "Matrica4::@6890427a1f51a3e7e1df",
					"jsonFile" : "target-Matrica4-Debug-594510da63b85e16de09.json",
					"name" : "Matrica4",
					"projectIndex" : 0
				},
				{
					"directoryIndex" : 0,
					"id" : "MinMaxNormalizacija::@6890427a1f51a3e7e1df",
					"jsonFile" : "target-MinMaxNormalizacija-Debug-949f58a411822c177f48.json",
					"name" : "MinMaxNormalizacija",
					"projectIndex" : 0
				},
				{
					"directoryIndex" : 0,
					"id" : "Morze::@6890427a1f51a3e7e1df",
					"jsonFile" : "target-Morze-Debug-2396b515d7fd61b3534d.json",
					"name" : "Morze",
					"projectIndex" : 0
				},
				{
					"directoryIndex" : 0,
					"id" : "NajgolemaKolona::@6890427a1f51a3e7e1df",
					"jsonFile" : "target-NajgolemaKolona-Debug-befee23217ece0014dd7.json",
					"name" : "NajgolemaKolona",
					"projectIndex" : 0
				},
				{
					"directoryIndex" : 0,
					"id" : "NegativniMatrica::@6890427a1f51a3e7e1df",
					"jsonFile" : "target-NegativniMatrica-Debug-d5e736b8f9247b79775c.json",
					"name" : "NegativniMatrica",
					"projectIndex" : 0
				},
				{
					"directoryIndex" : 0,
					"id" : "NeparniElementi::@6890427a1f51a3e7e1df",
					"jsonFile" : "target-NeparniElementi-Debug-8e31175a9b9619400d39.json",
					"name" : "NeparniElementi",
					"projectIndex" : 0
				},
				{
					"directoryIndex" : 0,
					"id" : "ObratnoSortiranje::@6890427a1f51a3e7e1df",
					"jsonFile" : "target-ObratnoSortiranje-Debug-508570f0a7ed94b06042.json",
					"name" : "ObratnoSortiranje",
					"projectIndex" : 0
				},
				{
					"directoryIndex" : 0,
					"id" : "OcenaSansa::@6890427a1f51a3e7e1df",
					"jsonFile" : "target-OcenaSansa-Debug-d62a8c507c7734f6ef72.json",
					"name" : "OcenaSansa",
					"projectIndex" : 0
				},
				{
					"directoryIndex" : 0,
					"id" : "OgledalnaNiza::@6890427a1f51a3e7e1df",
					"jsonFile" : "target-OgledalnaNiza-Debug-fc2d1a252f7394bacc1c.json",
					"name" : "OgledalnaNiza",
					"projectIndex" : 0
				},
				{
					"directoryIndex" : 0,
					"id" : "Oktomvri::@6890427a1f51a3e7e1df",
					"jsonFile" : "target-Oktomvri-Debug-cfabfcd424bef625b538.json",
					"name" : "Oktomvri",
					"projectIndex" : 0
				},
				{
					"directoryIndex" : 0,
					"id" : "Palindrom::@6890427a1f51a3e7e1df",
					"jsonFile" : "target-Palindrom-Debug-61a40c4e56709da28a30.json",
					"name" : "Palindrom",
					"projectIndex" : 0
				},
				{
					"directoryIndex" : 0,
					"id" : "Palindrom2::@6890427a1f51a3e7e1df",
					"jsonFile" : "target-Palindrom2-Debug-a6985502b77af62ea89e.json",
					"name" : "Palindrom2",
					"projectIndex" : 0
				},
				{
					"directoryIndex" : 0,
					"id" : "PalindromFunkcii::@6890427a1f51a3e7e1df",
					"jsonFile" : "target-PalindromFunkcii-Debug-785937480815aa98def7.json",
					"name" : "PalindromFunkcii",
					"projectIndex" : 0
				},
				{
					"directoryIndex" : 0,
					"id" : "ParnaMatrica::@6890427a1f51a3e7e1df",
					"jsonFile" : "target-ParnaMatrica-Debug-ad0173b2d9241658f853.json",
					"name" : "ParnaMatrica",
					"projectIndex" : 0
				},
				{
					"directoryIndex" : 0,
					"id" : "ParniNeparniNizi::@6890427a1f51a3e7e1df",
					"jsonFile" : "target-ParniNeparniNizi-Debug-30f1b08710b0c39621a2.json",
					"name" : "ParniNeparniNizi",
					"projectIndex" : 0
				},
				{
					"directoryIndex" : 0,
					"id" : "Parovi::@6890427a1f51a3e7e1df",
					"jsonFile" : "target-Parovi-Debug-9635a563984bd4941e78.json",
					"name" : "Parovi",
					"projectIndex" : 0
				},
				{
					"directoryIndex" : 0,
					"id" : "Pikseli::@6890427a1f51a3e7e1df",
					"jsonFile" : "target-Pikseli-Debug-d79b47d60e2f3ad18785.json",
					"name" : "Pikseli",
					"projectIndex" : 0
				},
				{
					"directoryIndex" : 0,
					"id" : "PodDijagonali::@6890427a1f51a3e7e1df",
					"jsonFile" : "target-PodDijagonali-Debug-168379c55bdb3e96ef0d.json",
					"name" : "PodDijagonali",
					"projectIndex" : 0
				},
				{
					"directoryIndex" : 0,
					"id" : "PodredenBr::@6890427a1f51a3e7e1df",
					"jsonFile" : "target-PodredenBr-Debug-725d3dd98ba9f5b70094.json",
					"name" : "PodredenBr",
					"projectIndex" : 0
				},
				{
					"directoryIndex" : 0,
					"id" : "PogolemiNiza::@6890427a1f51a3e7e1df",
					"jsonFile" : "target-PogolemiNiza-Debug-42bd5e0027c35120dcc0.json",
					"name" : "PogolemiNiza",
					"projectIndex" : 0
				},
				{
					"directoryIndex" : 0,
					"id" : "PolaPola::@6890427a1f51a3e7e1df",
					"jsonFile" : "target-PolaPola-Debug-72914f0d67a31ac53b39.json",
					"name" : "PolaPola",
					"projectIndex" : 0
				},
				{
					"directoryIndex" : 0,
					"id" : "PovtoruvanjeBukva::@6890427a1f51a3e7e1df",
					"jsonFile" : "target-PovtoruvanjeBukva-Debug-27d5813359d018248834.json",
					"name" : "PovtoruvanjeBukva",
					"projectIndex" : 0
				},
				{
					"directoryIndex" : 0,
					"id" : "ProsekCeni::@6890427a1f51a3e7e1df",
					"jsonFile" : "target-ProsekCeni-Debug-6e46833cc1b94ec428e6.json",
					"name" : "ProsekCeni",
					"projectIndex" : 0
				},
				{
					"directoryIndex" : 0,
					"id" : "ProstaNiza::@6890427a1f51a3e7e1df",
					"jsonFile" : "target-ProstaNiza-Debug-e3e79ac2c9f2a095fd53.json",
					"name" : "ProstaNiza",
					"projectIndex" : 0
				},
				{
					"directoryIndex" : 0,
					"id" : "RasteckaNiza::@6890427a1f51a3e7e1df",
					"jsonFile" : "target-RasteckaNiza-Debug-91272b29084be4a25afe.json",
					"name" : "RasteckaNiza",
					"projectIndex" : 0
				},
				{
					"directoryIndex" : 0,
					"id" : "Rekurzija::@6890427a1f51a3e7e1df",
					"jsonFile" : "target-Rekurzija-Debug-6ee9d0ac467d0ad86915.json",
					"name" : "Rekurzija",
					"projectIndex" : 0
				},
				{
					"directoryIndex" : 0,
					"id" : "Rekurzija1::@6890427a1f51a3e7e1df",
					"jsonFile" : "target-Rekurzija1-Debug-804a84d7b3fc41bde10f.json",
					"name" : "Rekurzija1",
					"projectIndex" : 0
				},
				{
					"directoryIndex" : 0,
					"id" : "Rekurzija2::@6890427a1f51a3e7e1df",
					"jsonFile" : "target-Rekurzija2-Debug-11b5903a42dd61e0cb1a.json",
					"name" : "Rekurzija2",
					"projectIndex" : 0
				},
				{
					"directoryIndex" : 0,
					"id" : "Rekurzija3::@6890427a1f51a3e7e1df",
					"jsonFile" : "target-Rekurzija3-Debug-5733c1dc918ba0b0fb97.json",
					"name" : "Rekurzija3",
					"projectIndex" : 0
				},
				{
					"directoryIndex" : 0,
					"id" : "Rekurzija4::@6890427a1f51a3e7e1df",
					"jsonFile" : "target-Rekurzija4-Debug-fe34c11287a58a3de9c5.json",
					"name" : "Rekurzija4",
					"projectIndex" : 0
				},
				{
					"directoryIndex" : 0,
					"id" : "Rekurzija5::@6890427a1f51a3e7e1df",
					"jsonFile" : "target-Rekurzija5-Debug-666356bd775334b8cb63.json",
					"name" : "Rekurzija5",
					"projectIndex" : 0
				},
				{
					"directoryIndex" : 0,
					"id" : "Rekurzija6::@6890427a1f51a3e7e1df",
					"jsonFile" : "target-Rekurzija6-Debug-9d5b292032a9e26bfdb3.json",
					"name" : "Rekurzija6",
					"projectIndex" : 0
				},
				{
					"directoryIndex" : 0,
					"id" : "Rekurzija7::@6890427a1f51a3e7e1df",
					"jsonFile" : "target-Rekurzija7-Debug-fa6f1e5c5ae4241e0df5.json",
					"name" : "Rekurzija7",
					"projectIndex" : 0
				},
				{
					"directoryIndex" : 0,
					"id" : "Rekurzija8::@6890427a1f51a3e7e1df",
					"jsonFile" : "target-Rekurzija8-Debug-2e0a086aad2e841f8f6d.json",
					"name" : "Rekurzija8",
					"projectIndex" : 0
				},
				{
					"directoryIndex" : 0,
					"id" : "Rekurzija9::@6890427a1f51a3e7e1df",
					"jsonFile" : "target-Rekurzija9-Debug-a8134ee16140f77abee6.json",
					"name" : "Rekurzija9",
					"projectIndex" : 0
				},
				{
					"directoryIndex" : 0,
					"id" : "RelativnaFrekvencija::@6890427a1f51a3e7e1df",
					"jsonFile" : "target-RelativnaFrekvencija-Debug-30b6eae8eb3deb156ca4.json",
					"name" : "RelativnaFrekvencija",
					"projectIndex" : 0
				},
				{
					"directoryIndex" : 0,
					"id" : "RotacijaNiza::@6890427a1f51a3e7e1df",
					"jsonFile" : "target-RotacijaNiza-Debug-480a7a3d8f6e545309c0.json",
					"name" : "RotacijaNiza",
					"projectIndex" : 0
				},
				{
					"directoryIndex" : 0,
					"id" : "Samoglaska::@6890427a1f51a3e7e1df",
					"jsonFile" : "target-Samoglaska-Debug-7a0cf4566de1f71d1cee.json",
					"name" : "Samoglaska",
					"projectIndex" : 0
				},
				{
					"directoryIndex" : 0,
					"id" : "Sifr_poraki::@6890427a1f51a3e7e1df",
					"jsonFile" : "target-Sifr_poraki-Debug-e579737f8738c1c3ee6a.json",
					"name" : "Sifr_poraki",
					"projectIndex" : 0
				},
				{
					"directoryIndex" : 0,
					"id" : "SpojuvanjeNizi::@6890427a1f51a3e7e1df",
					"jsonFile" : "target-SpojuvanjeNizi-Debug-735587b3ba1964dee9e0.json",
					"name" : "SpojuvanjeNizi",
					"projectIndex" : 0
				},
				{
					"directoryIndex" : 0,
					"id" : "SredenBroj::@6890427a1f51a3e7e1df",
					"jsonFile" : "target-SredenBroj-Debug-f29b9cb18bb1e8216932.json",
					"name" : "SredenBroj",
					"projectIndex" : 0
				},
				{
					"directoryIndex" : 0,
					"id" : "SredenBroj2::@6890427a1f51a3e7e1df",
					"jsonFile" : "target-SredenBroj2-Debug-0b0261a3b79e2e247dc0.json",
					"name" : "SredenBroj2",
					"projectIndex" : 0
				},
				{
					"directoryIndex" : 0,
					"id" : "SredinaOperaciiNacin1::@6890427a1f51a3e7e1df",
					"jsonFile" : "target-SredinaOperaciiNacin1-Debug-cce47f8675c0a3734e5d.json",
					"name" : "SredinaOperaciiNacin1",
					"projectIndex" : 0
				},
				{
					"directoryIndex" : 0,
					"id" : "SredinaOperaciiNacin2::@6890427a1f51a3e7e1df",
					"jsonFile" : "target-SredinaOperaciiNacin2-Debug-045378247bd019bbd0f6.json",
					"name" : "SredinaOperaciiNacin2",
					"projectIndex" : 0
				},
				{
					"directoryIndex" : 0,
					"id" : "Stepen::@6890427a1f51a3e7e1df",
					"jsonFile" : "target-Stepen-Debug-7eb60d47f4d04886bf8d.json",
					"name" : "Stepen",
					"projectIndex" : 0
				},
				{
					"directoryIndex" : 0,
					"id" : "Stringovi::@6890427a1f51a3e7e1df",
					"jsonFile" : "target-Stringovi-Debug-83ff5f9a5450280ed88d.json",
					"name" : "Stringovi",
					"projectIndex" : 0
				},
				{
					"directoryIndex" : 0,
					"id" : "Suma2Cifren::@6890427a1f51a3e7e1df",
					"jsonFile" : "target-Suma2Cifren-Debug-6d01cb7298476a4d2304.json",
					"name" : "Suma2Cifren",
					"projectIndex" : 0
				},
				{
					"directoryIndex" : 0,
					"id" : "Suma2NCifren::@6890427a1f51a3e7e1df",
					"jsonFile" : "target-Suma2NCifren-Debug-7f3fde8c75d9cf4d9fe5.json",
					"name" : "Suma2NCifren",
					"projectIndex" : 0
				},
				{
					"directoryIndex" : 0,
					"id" : "SumaSoInterval::@6890427a1f51a3e7e1df",
					"jsonFile" : "target-SumaSoInterval-Debug-dee81b7627ba01e52e83.json",
					"name" : "SumaSoInterval",
					"projectIndex" : 0
				},
				{
					"directoryIndex" : 0,
					"id" : "TelefonskiBroevi::@6890427a1f51a3e7e1df",
					"jsonFile" : "target-TelefonskiBroevi-Debug-77933ba56b01a8379a14.json",
					"name" : "TelefonskiBroevi",
					"projectIndex" : 0
				},
				{
					"directoryIndex" : 0,
					"id" : "UpisFINKI::@6890427a1f51a3e7e1df",
					"jsonFile" : "target-UpisFINKI-Debug-df10f6b03be830354df3.json",
					"name" : "UpisFINKI",
					"projectIndex" : 0
				},
				{
					"directoryIndex" : 0,
					"id" : "Vraboteni::@6890427a1f51a3e7e1df",
					"jsonFile" : "target-Vraboteni-Debug-64ed5a5437b2801f8d94.json",
					"name" : "Vraboteni",
					"projectIndex" : 0
				},
				{
					"directoryIndex" : 0,
					"id" : "Z1::@6890427a1f51a3e7e1df",
					"jsonFile" : "target-Z1-Debug-2f489881e0d700f163a2.json",
					"name" : "Z1",
					"projectIndex" : 0
				},
				{
					"directoryIndex" : 0,
					"id" : "Z10::@6890427a1f51a3e7e1df",
					"jsonFile" : "target-Z10-Debug-7b7c5187c81f6605ccce.json",
					"name" : "Z10",
					"projectIndex" : 0
				},
				{
					"directoryIndex" : 0,
					"id" : "Z2::@6890427a1f51a3e7e1df",
					"jsonFile" : "target-Z2-Debug-96258286da01a04c0242.json",
					"name" : "Z2",
					"projectIndex" : 0
				},
				{
					"directoryIndex" : 0,
					"id" : "Z7::@6890427a1f51a3e7e1df",
					"jsonFile" : "target-Z7-Debug-d76c2a6a05d73796f027.json",
					"name" : "Z7",
					"projectIndex" : 0
				},
				{
					"directoryIndex" : 0,
					"id" : "Z9::@6890427a1f51a3e7e1df",
					"jsonFile" : "target-Z9-Debug-d28fae3c9e5bd10d29d4.json",
					"name" : "Z9",
					"projectIndex" : 0
				},
				{
					"directoryIndex" : 0,
					"id" : "Zad1::@6890427a1f51a3e7e1df",
					"jsonFile" : "target-Zad1-Debug-d3ef22c5cfeb92705ef5.json",
					"name" : "Zad1",
					"projectIndex" : 0
				},
				{
					"directoryIndex" : 0,
					"id" : "Zad2::@6890427a1f51a3e7e1df",
					"jsonFile" : "target-Zad2-Debug-6cb2117f57410a2cdcd2.json",
					"name" : "Zad2",
					"projectIndex" : 0
				},
				{
					"directoryIndex" : 0,
					"id" : "Zad3::@6890427a1f51a3e7e1df",
					"jsonFile" : "target-Zad3-Debug-d1da5885a5486ebc1a30.json",
					"name" : "Zad3",
					"projectIndex" : 0
				},
				{
					"directoryIndex" : 0,
					"id" : "Zad4::@6890427a1f51a3e7e1df",
					"jsonFile" : "target-Zad4-Debug-239c09bf7bf18fce10e3.json",
					"name" : "Zad4",
					"projectIndex" : 0
				},
				{
					"directoryIndex" : 0,
					"id" : "ZbirIndeks::@6890427a1f51a3e7e1df",
					"jsonFile" : "target-ZbirIndeks-Debug-2b6dae42aabdd79e7038.json",
					"name" : "ZbirIndeks",
					"projectIndex" : 0
				},
				{
					"directoryIndex" : 0,
					"id" : "ZbirPodNiza::@6890427a1f51a3e7e1df",
					"jsonFile" : "target-ZbirPodNiza-Debug-00842539065199bf6ab6.json",
					"name" : "ZbirPodNiza",
					"projectIndex" : 0
				},
				{
					"directoryIndex" : 0,
					"id" : "Zigazaga::@6890427a1f51a3e7e1df",
					"jsonFile" : "target-Zigazaga-Debug-6c677c892d021cecf707.json",
					"name" : "Zigazaga",
					"projectIndex" : 0
				},
				{
					"directoryIndex" : 0,
					"id" : "ZnaciZadaca::@6890427a1f51a3e7e1df",
					"jsonFile" : "target-ZnaciZadaca-Debug-0ce4a39f4f0f91116f1e.json",
					"name" : "ZnaciZadaca",
					"projectIndex" : 0
				},
				{
					"directoryIndex" : 0,
					"id" : "ZnakDijagonali::@6890427a1f51a3e7e1df",
					"jsonFile" : "target-ZnakDijagonali-Debug-42f5862a0599e6b43791.json",
					"name" : "ZnakDijagonali",
					"projectIndex" : 0
				},
				{
					"directoryIndex" : 0,
					"id" : "kElement::@6890427a1f51a3e7e1df",
					"jsonFile" : "target-kElement-Debug-98a70f6dcfea6906db44.json",
					"name" : "kElement",
					"projectIndex" : 0
				},
				{
					"directoryIndex" : 0,
					"id" : "kTrampa::@6890427a1f51a3e7e1df",
					"jsonFile" : "target-kTrampa-Debug-06e329bbbfce33b6911d.json",
					"name" : "kTrampa",
					"projectIndex" : 0
				}
			]
		}
	],
	"kind" : "codemodel",
	"paths" : 
	{
		"build" : "C:/Users/Media/CLionProjects/SP2023/cmake-build-debug",
		"source" : "C:/Users/Media/CLionProjects/SP2023"
	},
	"version" : 
	{
		"major" : 2,
		"minor" : 6
	}
}
